<?xml version="1.0" encoding="UTF-8"?>
<!DOCTYPE plist PUBLIC "-//Apple//DTD PLIST 1.0//EN" "http://www.apple.com/DTDs/PropertyList-1.0.dtd"/>

<plist version="1.0">
    <dict>
        <key>ROOT</key>
        <array>
            <dict>
                <key>id</key>
                <string>11961</string>
                <key>className</key>
                <string>PTModelObjectCharacterSelector</string>
                <key>Name</key>
                <dict>
                    <key>value</key>
                    <string>Multiple Unlock</string>
                </dict>
                <key>Position</key>
                <dict>
                    <key>value</key>
                    <string>{184.181,703.712}</string>
                </dict>
                <key>Scale</key>
                <dict>
                    <key>value</key>
                    <string>{1.000,1.000}</string>
                </dict>
                <key>Hidden</key>
                <dict>
                    <key>visible</key>
                    <string>0</string>
                </dict>
                <key>Locked</key>
                <dict>
                    <key>visible</key>
                    <string>0</string>
                </dict>
                <key>Label Name</key>
                <dict>
                    <key>selectedStringValue</key>
                    <string>2</string>
                </dict>
                <key>zDepth</key>
                <string>0</string>
            </dict>
            <dict>
                <key>id</key>
                <string>18450</string>
                <key>className</key>
                <string>PTModelObjectCharacterSelector</string>
                <key>Name</key>
                <dict>
                    <key>value</key>
                    <string>Multiple Unlock</string>
                </dict>
                <key>Position</key>
                <dict>
                    <key>value</key>
                    <string>{328.399,542.119}</string>
                </dict>
                <key>Scale</key>
                <dict>
                    <key>value</key>
                    <string>{1.000,1.000}</string>
                </dict>
                <key>Hidden</key>
                <dict>
                    <key>visible</key>
                    <string>0</string>
                </dict>
                <key>Locked</key>
                <dict>
                    <key>visible</key>
                    <string>0</string>
                </dict>
                <key>Label Name</key>
                <dict>
                    <key>selectedStringValue</key>
                    <string>2</string>
                </dict>
                <key>zDepth</key>
                <string>12</string>
            </dict>
            <dict>
                <key>id</key>
                <string>18452</string>
                <key>className</key>
                <string>PTModelObjectCharacterSelector</string>
                <key>Name</key>
                <dict>
                    <key>value</key>
                    <string>Multiple Unlock</string>
                </dict>
                <key>Position</key>
                <dict>
                    <key>value</key>
                    <string>{320.000,531.482}</string>
                    <key>animationsX</key>
                    <array/>
                    <key>animationsY</key>
                    <array/>
                </dict>
                <key>Rotation</key>
                <dict>
                    <key>animations</key>
                    <array/>
                </dict>
                <key>Scale</key>
                <dict>
                    <key>value</key>
                    <string>{5.650,1.526}</string>
                    <key>animationsX</key>
                    <array/>
                    <key>animationsY</key>
                    <array/>
                </dict>
                <key>Hidden</key>
                <dict>
                    <key>visible</key>
                    <string>0</string>
                </dict>
                <key>Locked</key>
                <dict>
                    <key>visible</key>
                    <string>0</string>
                </dict>
                <key>Opacity</key>
                <dict>
                    <key>value</key>
                    <string>0.800000</string>
                    <key>animations</key>
                    <array/>
                </dict>
                <key>Label Vertical Spacing</key>
                <dict>
                    <key>value</key>
                    <string>44.000000</string>
                </dict>
                <key>Label Name</key>
                <dict>
                    <key>selectedStringValue</key>
                    <string>14276</string>
                </dict>
                <key>Spread</key>
                <dict>
                    <key>value</key>
                    <string>125.000000</string>
                </dict>
                <key>zDepth</key>
                <string>13</string>
            </dict>
            <dict>
                <key>id</key>
                <string>20062</string>
                <key>className</key>
                <string>PTModelObjectCharacterSelector</string>
                <key>Name</key>
                <dict>
                    <key>value</key>
                    <string>Multiple Unlock</string>
                </dict>
                <key>Position</key>
                <dict>
                    <key>value</key>
                    <string>{320.000,531.482}</string>
                </dict>
                <key>Scale</key>
                <dict>
                    <key>value</key>
                    <string>{5.456,1.526}</string>
                </dict>
                <key>Hidden</key>
                <dict>
                    <key>visible</key>
                    <string>0</string>
                </dict>
                <key>Locked</key>
                <dict>
                    <key>visible</key>
                    <string>0</string>
                </dict>
                <key>Opacity</key>
                <dict>
                    <key>value</key>
                    <string>0.800000</string>
                </dict>
                <key>Label Vertical Spacing</key>
                <dict>
                    <key>value</key>
                    <string>44.000000</string>
                </dict>
                <key>Label Name</key>
                <dict>
                    <key>selectedStringValue</key>
                    <string>14276</string>
                </dict>
                <key>Spread</key>
                <dict>
                    <key>value</key>
                    <string>110.000000</string>
                </dict>
                <key>zDepth</key>
                <string>10</string>
            </dict>
        </array>
    </dict>
</plist>
