<?xml version="1.0" encoding="UTF-8"?>
<!DOCTYPE plist PUBLIC "-//Apple//DTD PLIST 1.0//EN" "http://www.apple.com/DTDs/PropertyList-1.0.dtd"/>

<plist version="1.0">
    <dict>
        <key>ROOT</key>
        <array>
            <dict>
                <key>id</key>
                <string>145</string>
                <key>sprites</key>
                <array>
                    <string>146</string>
                </array>
            </dict>
            <dict>
                <key>id</key>
                <string>154</string>
                <key>sprites</key>
                <array>
                    <string>155</string>
                </array>
            </dict>
            <dict>
                <key>id</key>
                <string>10910</string>
                <key>sprites</key>
                <array>
                    <string>10911</string>
                </array>
            </dict>
            <dict>
                <key>id</key>
                <string>10927</string>
                <key>sprites</key>
                <array>
                    <string>10928</string>
                </array>
            </dict>
            <dict>
                <key>id</key>
                <string>11113</string>
                <key>sprites</key>
                <array>
                    <string>11114</string>
                </array>
            </dict>
            <dict>
                <key>id</key>
                <string>11344</string>
                <key>sprites</key>
                <array>
                    <string>11345</string>
                </array>
            </dict>
            <dict>
                <key>id</key>
                <string>12022</string>
                <key>sprites</key>
                <array>
                    <string>12023</string>
                </array>
            </dict>
            <dict>
                <key>id</key>
                <string>13992</string>
                <key>sprites</key>
                <array>
                    <string>13993</string>
                </array>
            </dict>
            <dict>
                <key>id</key>
                <string>14001</string>
                <key>sprites</key>
                <array>
                    <string>14002</string>
                </array>
            </dict>
            <dict>
                <key>id</key>
                <string>14027</string>
                <key>sprites</key>
                <array>
                    <string>14028</string>
                </array>
            </dict>
            <dict>
                <key>id</key>
                <string>14033</string>
                <key>sprites</key>
                <array>
                    <string>14034</string>
                </array>
            </dict>
            <dict>
                <key>id</key>
                <string>14058</string>
                <key>sprites</key>
                <array>
                    <string>14059</string>
                </array>
            </dict>
            <dict>
                <key>id</key>
                <string>14388</string>
                <key>sprites</key>
                <array>
                    <string>14389</string>
                </array>
            </dict>
            <dict>
                <key>id</key>
                <string>14534</string>
                <key>sprites</key>
                <array>
                    <string>14535</string>
                </array>
            </dict>
            <dict>
                <key>id</key>
                <string>14582</string>
                <key>sprites</key>
                <array>
                    <string>14583</string>
                </array>
            </dict>
            <dict>
                <key>id</key>
                <string>14625</string>
                <key>sprites</key>
                <array>
                    <string>14626</string>
                </array>
            </dict>
            <dict>
                <key>id</key>
                <string>14658</string>
                <key>sprites</key>
                <array>
                    <string>14659</string>
                </array>
            </dict>
            <dict>
                <key>id</key>
                <string>14677</string>
                <key>sprites</key>
                <array>
                    <string>14678</string>
                </array>
            </dict>
            <dict>
                <key>id</key>
                <string>14697</string>
                <key>sprites</key>
                <array>
                    <string>14698</string>
                </array>
            </dict>
            <dict>
                <key>id</key>
                <string>15234</string>
                <key>sprites</key>
                <array>
                    <string>15235</string>
                </array>
            </dict>
            <dict>
                <key>id</key>
                <string>15414</string>
                <key>sprites</key>
                <array>
                    <string>15415</string>
                </array>
            </dict>
            <dict>
                <key>id</key>
                <string>15419</string>
                <key>sprites</key>
                <array>
                    <string>15420</string>
                </array>
            </dict>
            <dict>
                <key>id</key>
                <string>15424</string>
                <key>sprites</key>
                <array>
                    <string>15425</string>
                </array>
            </dict>
            <dict>
                <key>id</key>
                <string>15511</string>
                <key>sprites</key>
                <array>
                    <string>15512</string>
                </array>
            </dict>
            <dict>
                <key>id</key>
                <string>16731</string>
                <key>sprites</key>
                <array>
                    <string>16732</string>
                </array>
            </dict>
            <dict>
                <key>id</key>
                <string>16749</string>
                <key>sprites</key>
                <array>
                    <string>16750</string>
                </array>
            </dict>
            <dict>
                <key>id</key>
                <string>16859</string>
                <key>sprites</key>
                <array>
                    <string>16860</string>
                </array>
            </dict>
            <dict>
                <key>id</key>
                <string>17247</string>
                <key>sprites</key>
                <array>
                    <string>17248</string>
                </array>
            </dict>
            <dict>
                <key>id</key>
                <string>17378</string>
                <key>sprites</key>
                <array>
                    <string>17379</string>
                </array>
            </dict>
            <dict>
                <key>id</key>
                <string>18437</string>
                <key>sprites</key>
                <array>
                    <string>18438</string>
                </array>
            </dict>
            <dict>
                <key>id</key>
                <string>18454</string>
                <key>sprites</key>
                <array>
                    <string>18455</string>
                </array>
            </dict>
            <dict>
                <key>id</key>
                <string>18470</string>
                <key>sprites</key>
                <array>
                    <string>18471</string>
                </array>
            </dict>
            <dict>
                <key>id</key>
                <string>18729</string>
                <key>sprites</key>
                <array>
                    <string>18730</string>
                </array>
            </dict>
            <dict>
                <key>id</key>
                <string>18749</string>
                <key>sprites</key>
                <array>
                    <string>18750</string>
                </array>
            </dict>
            <dict>
                <key>id</key>
                <string>18753</string>
                <key>sprites</key>
                <array>
                    <string>18754</string>
                </array>
            </dict>
            <dict>
                <key>id</key>
                <string>18757</string>
                <key>sprites</key>
                <array>
                    <string>18758</string>
                </array>
            </dict>
            <dict>
                <key>id</key>
                <string>18761</string>
                <key>sprites</key>
                <array>
                    <string>18762</string>
                </array>
            </dict>
            <dict>
                <key>id</key>
                <string>19027</string>
                <key>sprites</key>
                <array>
                    <string>19028</string>
                </array>
            </dict>
            <dict>
                <key>id</key>
                <string>19187</string>
                <key>sprites</key>
                <array>
                    <string>19188</string>
                </array>
            </dict>
            <dict>
                <key>id</key>
                <string>19352</string>
                <key>sprites</key>
                <array>
                    <string>19353</string>
                </array>
            </dict>
            <dict>
                <key>id</key>
                <string>19571</string>
                <key>sprites</key>
                <array>
                    <string>19572</string>
                </array>
            </dict>
            <dict>
                <key>id</key>
                <string>19873</string>
                <key>sprites</key>
                <array>
                    <string>19874</string>
                </array>
            </dict>
            <dict>
                <key>id</key>
                <string>19900</string>
                <key>sprites</key>
                <array>
                    <string>19901</string>
                </array>
            </dict>
            <dict>
                <key>id</key>
                <string>19921</string>
                <key>sprites</key>
                <array>
                    <string>19922</string>
                </array>
            </dict>
        </array>
    </dict>
</plist>
